kehe_fl/__init__.py
kehe_fl/comms/__init__.py
kehe_fl/comms/mqtt_agg_server.py
kehe_fl/comms/mqtt_device.py
kehe_fl/comms/mqtt_provider.py
kehe_fl/comms/enum/__init__.py
kehe_fl/comms/enum/mqtt_cmd_enum.py
kehe_fl/comms/enum/mqtt_status_enum.py
kehe_fl/utils/__init__.py
kehe_fl/utils/common/__init__.py
kehe_fl/utils/common/adafruit_scd_30.py
kehe_fl/utils/common/data_storage.py
kehe_fl/utils/common/project_constants.py
kehe_fl/utils/service/__init__.py
kehe_fl/utils/service/data_collection_service.py
kehe_fl/utils/service/model_service.py
kehe_fl/utils/service/monitoring_service.py
kehe_fl_s2/__init__.py
kehe_fl_s2/comms/__init__.py
kehe_fl_s2/comms/mqtt_agg_server.py
kehe_fl_s2/comms/mqtt_device.py
kehe_fl_s2/comms/mqtt_provider.py
kehe_fl_s2/comms/enum/__init__.py
kehe_fl_s2/comms/enum/mqtt_cmd_enum.py
kehe_fl_s2/comms/enum/mqtt_status_enum.py
kehe_fl_s2/utils/__init__.py
kehe_fl_s2/utils/common/__init__.py
kehe_fl_s2/utils/common/adafruit_scd_30.py
kehe_fl_s2/utils/common/data_storage.py
kehe_fl_s2/utils/common/project_constants.py
kehe_fl_s2/utils/service/__init__.py
kehe_fl_s2/utils/service/data_collection_service.py
kehe_fl_s2/utils/service/model_service.py
kehe_fl_s2/utils/service/monitoring_service.py
kehe_fl_s3/__init__.py
kehe_fl_s3/comms/__init__.py
kehe_fl_s3/comms/mqtt_agg_server.py
kehe_fl_s3/comms/mqtt_device.py
kehe_fl_s3/comms/mqtt_provider.py
kehe_fl_s3/comms/enum/__init__.py
kehe_fl_s3/comms/enum/mqtt_cmd_enum.py
kehe_fl_s3/comms/enum/mqtt_status_enum.py
kehe_fl_s3/utils/__init__.py
kehe_fl_s3/utils/common/__init__.py
kehe_fl_s3/utils/common/adafruit_scd_30.py
kehe_fl_s3/utils/common/data_storage.py
kehe_fl_s3/utils/common/project_constants.py
kehe_fl_s3/utils/service/__init__.py
kehe_fl_s3/utils/service/data_collection_service.py
kehe_fl_s3/utils/service/model_service.py
kehe_fl_s3/utils/service/monitoring_service.py
kehe_fl-0.1.14.dist-info/METADATA
kehe_fl-0.1.14.dist-info/WHEEL
kehe_fl-0.1.14.dist-info/top_level.txt
kehe_fl-0.1.14.dist-info/RECORD
