Metadata-Version: 2.4
Name: kehe-fl
Version: 0.1.14
Summary: A federated learning package for IoT devices and aggregation server communication.
Home-page: https://github.com/ke-he/kehe-fl
Author: Kevin Hetzenauer
Author-email: kevin@hetzenauer.me
Classifier: Programming Language :: Python :: 3
Classifier: Operating System :: OS Independent
Requires-Dist: aiomqtt
Dynamic: author
Dynamic: author-email
Dynamic: classifier
Dynamic: description
Dynamic: description-content-type
Dynamic: home-page
Dynamic: requires-dist
Dynamic: summary
